LICENSE
README.md
getise/__init__.py
getise/cli.py
getise/exceptions.py
getise-2.0.0.dist-info/LICENSE
getise-2.0.0.dist-info/METADATA
getise-2.0.0.dist-info/WHEEL
getise-2.0.0.dist-info/entry_points.txt
getise-2.0.0.dist-info/RECORD
